test_option_deps/__init__.py
test_option_deps-3.0.0.dist-info/METADATA
test_option_deps-3.0.0.dist-info/WHEEL
test_option_deps-3.0.0.dist-info/entry_points.txt
test_option_deps-3.0.0.dist-info/RECORD
