Metadata-Version: 2.1
Name: test-option-deps
Version: 3.0.0
Summary: Testing optional dependencies
Author: Saipraneeth
Author-email: 2506664+msaipraneeth@users.noreply.github.com
Requires-Python: >=3.11,<4.0
Classifier: Programming Language :: Python :: 3
Classifier: Programming Language :: Python :: 3.11
Classifier: Programming Language :: Python :: 3.12
Provides-Extra: all
Requires-Dist: smart-open (>=7.0.4,<8.0.0) ; extra == "all"
Requires-Dist: smart-open[all] (>=7.0.4,<8.0.0) ; extra == "all"
